LICENSE
MANIFEST.in
README.rst
macaron.py
setup.py
macaron.egg-info/PKG-INFO
macaron.egg-info/SOURCES.txt
macaron.egg-info/dependency_links.txt
macaron.egg-info/top_level.txt
test/test_basic.py
test/test_class_attr.py
test/test_convert.py
test/test_fields.py
test/test_history.py
test/testall.py