Metadata-Version: 1.0
Name: macaron
Version: 0.3.1
Summary: Simple object-relational mapper for SQLite3, includes plugin for Bottle web framework
Home-page: http://nobrin.github.com/macaron
Author: Nobuo Okazaki
Author-email: nobrin@biokids.org
License: MIT
Platform: any
Classifier: Development Status :: 3 - Alpha
Classifier: Intended Audience :: Developers
Classifier: License :: OSI Approved :: MIT License
Classifier: Topic :: Database
Classifier: Topic :: Database :: Front-Ends
Classifier: Topic :: Software Development :: Libraries :: Python Modules
Classifier: Programming Language :: Python :: 2.5
Classifier: Programming Language :: Python :: 2.6
Classifier: Programming Language :: Python :: 2.7
